CHANGES.txt
MANIFEST.in
README.txt
TODO.txt
setup.cfg
setup.py
anybox/__init__.py
anybox.testing.datetime.egg-info/PKG-INFO
anybox.testing.datetime.egg-info/SOURCES.txt
anybox.testing.datetime.egg-info/dependency_links.txt
anybox.testing.datetime.egg-info/namespace_packages.txt
anybox.testing.datetime.egg-info/not-zip-safe
anybox.testing.datetime.egg-info/requires.txt
anybox.testing.datetime.egg-info/top_level.txt
anybox/testing/__init__.py
anybox/testing/datetime/__init__.py
anybox/testing/datetime/mock_dt.py
anybox/testing/datetime/mock_time.py
anybox/testing/datetime/sqlite3.py