Metadata-Version: 1.1
Name: anybox.testing.datetime
Version: 0.4.2
Summary: Various utilities related to date and time for testing purposes.
Home-page: https://bitbucket.org/anybox/anybox.testing.datetime
Author: Georges Racinet
Author-email: gracinet@anybox.fr
License: GPLv3+
Platform: UNKNOWN
Classifier: License :: OSI Approved :: GNU General Public License v3 or later (GPLv3+)
Classifier: Topic :: Software Development :: Testing
